opends/__init__.py
opends/opends.py
opends/sdk.py
opends-0.0.1.dist-info/DESCRIPTION.rst
opends-0.0.1.dist-info/METADATA
opends-0.0.1.dist-info/RECORD
opends-0.0.1.dist-info/WHEEL
opends-0.0.1.dist-info/metadata.json
opends-0.0.1.dist-info/top_level.txt
