Metadata-Version: 2.0
Name: opends
Version: 0.0.1
Summary: Official OpenDS REST API Client
Home-page: http://www.bdp.cn/
Author: bdp
Author-email: huangwenda@haizhi.com
License: UNKNOWN
Platform: UNKNOWN
Requires-Dist: requests
